psgr/__init__.py
psgr/genpass.py
psgr/main.py
psgr-0.2.2.dist-info/METADATA
psgr-0.2.2.dist-info/WHEEL
psgr-0.2.2.dist-info/entry_points.txt
psgr-0.2.2.dist-info/top_level.txt
psgr-0.2.2.dist-info/RECORD
