Metadata-Version: 2.1
Name: psgr
Version: 0.2.2
Summary: A password manager application
Author: Naresh Karthigeyan
Author-email: nareskarthigeyan.2005@gmail.com
Requires-Dist: InquirerPy
Requires-Dist: rsa
Requires-Dist: tabulate
